leaf/__init__.py
leaf/adapters/__init__.py
leaf/adapters/core_adapters/__init__.py
leaf/adapters/core_adapters/continuous_experiment_adapter.py
leaf/adapters/core_adapters/discrete_experiment_adapter.py
leaf/adapters/core_adapters/upload_adapter.py
leaf/adapters/equipment_adapter.py
leaf/config/configuration.yaml
leaf/data/marketplace.yaml
leaf/error_handler/__init__.py
leaf/error_handler/error_holder.py
leaf/error_handler/exceptions.py
leaf/measurement_handler/__init__.py
leaf/measurement_handler/handler.py
leaf/measurement_handler/measurements.yaml
leaf/measurement_handler/terms.py
leaf/modules/.gitkeep
leaf/modules/__init__.py
leaf/modules/input_modules/__init__.py
leaf/modules/input_modules/db_watcher.py
leaf/modules/input_modules/event_watcher.py
leaf/modules/input_modules/external_api_watcher.py
leaf/modules/input_modules/external_event_watcher.py
leaf/modules/input_modules/file_watcher.py
leaf/modules/input_modules/http_watcher.py
leaf/modules/input_modules/mqtt_external_event_watcher.py
leaf/modules/input_modules/mqtt_watcher.py
leaf/modules/input_modules/opc_watcher.py
leaf/modules/input_modules/polling_watcher.py
leaf/modules/input_modules/simple_watcher.py
leaf/modules/measurement_modules/__init__.py
leaf/modules/measurement_modules/carbon_dioxide.py
leaf/modules/measurement_modules/dissolved_oxygen.py
leaf/modules/measurement_modules/fluorescence.py
leaf/modules/measurement_modules/measurement_module.py
leaf/modules/measurement_modules/optical_density.py
leaf/modules/measurement_modules/ph.py
leaf/modules/measurement_modules/temperature.py
leaf/modules/output_modules/__init__.py
leaf/modules/output_modules/file.py
leaf/modules/output_modules/keydb.py
leaf/modules/output_modules/mqtt.py
leaf/modules/output_modules/output_module.py
leaf/modules/output_modules/sql.py
leaf/modules/phase_modules/__init__.py
leaf/modules/phase_modules/control.py
leaf/modules/phase_modules/error.py
leaf/modules/phase_modules/external_event_phase.py
leaf_framework-0.1.9.6.dist-info/METADATA
leaf_framework-0.1.9.6.dist-info/WHEEL
leaf_framework-0.1.9.6.dist-info/entry_points.txt
leaf_framework-0.1.9.6.dist-info/licenses/LICENSE
leaf_framework-0.1.9.6.dist-info/RECORD
